audiometer-0.17.0.dist-info/METADATA
audiometer-0.17.0.dist-info/WHEEL
audiometer/_audiometer.pyi
audiometer/py.typed
audiometer/__init__.py
audiometer/_audiometer.cpython-312-aarch64-linux-gnu.so
audiometer-0.17.0.dist-info/RECORD
