Metadata-Version: 2.4
Name: audiometer
Version: 0.17.0
Classifier: Topic :: Multimedia :: Sound/Audio
Classifier: Topic :: Multimedia :: Sound/Audio :: Analysis
Classifier: Topic :: Software Development :: Libraries
Requires-Dist: pydub ==0.25.1 ; extra == 'dev'
Requires-Dist: maturin ==1.2.3 ; extra == 'dev'
Requires-Dist: pre-commit ==3.4.0 ; extra == 'dev'
Requires-Dist: pytest ==7.4.2 ; extra == 'dev'
Provides-Extra: dev
Requires-Python: >=3.10
